onealgo/__init__.py
onealgo-0.0.1.dist-info/METADATA
onealgo-0.0.1.dist-info/WHEEL
onealgo-0.0.1.dist-info/RECORD
