Metadata-Version: 2.4
Name: onealgo
Version: 0.0.1
Summary: Full-stack algo trading: simulation, optimization, live execution.
Requires-Python: >=3.10
